zhudb
