Metadata-Version: 1.0
Name: zhudb
Version: 0.1.8
Summary: A sql tool in python3
Home-page: https://github.com/wenzhuart/zhudb
Author: bamboo
Author-email: wenzhu_art@hotmail.com
License: UNKNOWN
Platform: UNKNOWN
